{
  "name": "ClimateManager$ClimateNetAuth",
  "package": "zombie.iso.weather",
  "type": "class",
  "scope": "public",
  "describe": [
    "final"
  ],
  "extends": [
    "java.lang.Enum<zombie.iso.weather.ClimateManager$ClimateNetAuth>"
  ],
  "implements": [],
  "constructors": [
    {
      "scope": "package",
      "name": "values",
      "describe": [],
      "args": []
    }
  ],
  "fields": [
    {
      "name": "Denied",
      "scope": "public",
      "type": "zombie.iso.weather.ClimateManager$ClimateNetAuth",
      "describe": [
        "static",
        "final"
      ]
    },
    {
      "name": "ClientOnly",
      "scope": "public",
      "type": "zombie.iso.weather.ClimateManager$ClimateNetAuth",
      "describe": [
        "static",
        "final"
      ]
    },
    {
      "name": "ServerOnly",
      "scope": "public",
      "type": "zombie.iso.weather.ClimateManager$ClimateNetAuth",
      "describe": [
        "static",
        "final"
      ]
    },
    {
      "name": "ClientAndServer",
      "scope": "public",
      "type": "zombie.iso.weather.ClimateManager$ClimateNetAuth",
      "describe": [
        "static",
        "final"
      ]
    }
  ],
  "methods": [
    {
      "scope": "public",
      "describe": [
        "static"
      ],
      "return": "zombie.iso.weather.ClimateManager$ClimateNetAuth",
      "name": "valueOf",
      "args": [
        "java.lang.String"
      ]
    }
  ]
}