{
  "name": "ZomboidFileSystem$1",
  "package": "zombie",
  "type": "class",
  "scope": "package",
  "describe": [],
  "extends": [],
  "implements": [
    "java.nio.file.DirectoryStream$Filter<java.nio.file.Path>"
  ],
  "constructors": [],
  "fields": [],
  "methods": [
    {
      "scope": "public",
      "describe": [],
      "return": "boolean",
      "name": "accept",
      "args": [
        "java.nio.file.Path"
      ]
    },
    {
      "scope": "public",
      "describe": [],
      "return": "boolean",
      "name": "accept",
      "args": [
        "java.lang.Object"
      ]
    }
  ]
}