{
  "name": "FliesSound",
  "package": "zombie",
  "type": "class",
  "scope": "public",
  "describe": [
    "final"
  ],
  "extends": [],
  "implements": [],
  "constructors": [
    {
      "scope": "package",
      "name": "FliesSound",
      "describe": [],
      "args": []
    }
  ],
  "fields": [
    {
      "name": "instance",
      "scope": "public",
      "type": "zombie.FliesSound",
      "describe": [
        "static",
        "final"
      ]
    }
  ],
  "methods": [
    {
      "scope": "public",
      "describe": [],
      "return": "void",
      "name": "Reset",
      "args": []
    },
    {
      "scope": "public",
      "describe": [],
      "return": "void",
      "name": "update",
      "args": []
    },
    {
      "scope": "public",
      "describe": [],
      "return": "void",
      "name": "render",
      "args": []
    },
    {
      "scope": "public",
      "describe": [],
      "return": "void",
      "name": "chunkLoaded",
      "args": [
        "zombie.iso.IsoChunk"
      ]
    },
    {
      "scope": "public",
      "describe": [],
      "return": "void",
      "name": "corpseAdded",
      "args": [
        "int",
        "int",
        "int"
      ]
    },
    {
      "scope": "public",
      "describe": [],
      "return": "void",
      "name": "corpseRemoved",
      "args": [
        "int",
        "int",
        "int"
      ]
    },
    {
      "scope": "public",
      "describe": [],
      "return": "int",
      "name": "getCorpseCount",
      "args": [
        "zombie.characters.IsoGameCharacter"
      ]
    }
  ]
}