{
  "name": "ComboItem",
  "package": "zombie.inventory.types",
  "type": "class",
  "scope": "public",
  "describe": [
    "final"
  ],
  "extends": [
    "zombie.inventory.InventoryItem"
  ],
  "implements": [],
  "constructors": [
    {
      "scope": "package",
      "name": "ComboItem",
      "describe": [],
      "args": [
        "java.lang.String",
        "java.lang.String",
        "java.lang.String",
        "java.lang.String"
      ]
    },
    {
      "scope": "package",
      "name": "ComboItem",
      "describe": [],
      "args": [
        "java.lang.String",
        "java.lang.String",
        "java.lang.String",
        "zombie.scripting.objects.Item"
      ]
    }
  ],
  "fields": [],
  "methods": [
    {
      "scope": "public",
      "describe": [],
      "return": "int",
      "name": "getSaveType",
      "args": []
    }
  ]
}