{
  "name": "KeyboardStateCache",
  "package": "zombie.input",
  "type": "class",
  "scope": "public",
  "describe": [
    "final"
  ],
  "extends": [],
  "implements": [],
  "constructors": [
    {
      "scope": "package",
      "name": "KeyboardStateCache",
      "describe": [],
      "args": []
    }
  ],
  "fields": [],
  "methods": [
    {
      "scope": "public",
      "describe": [],
      "return": "void",
      "name": "poll",
      "args": []
    },
    {
      "scope": "public",
      "describe": [],
      "return": "void",
      "name": "swap",
      "args": []
    },
    {
      "scope": "public",
      "describe": [],
      "return": "zombie.input.KeyboardState",
      "name": "getState",
      "args": []
    },
    {
      "scope": "public",
      "describe": [],
      "return": "zombie.input.KeyboardState",
      "name": "getStatePolling",
      "args": []
    }
  ]
}