{
  "name": "CharacterSmartTexture",
  "package": "zombie.characterTextures",
  "type": "class",
  "scope": "public",
  "describe": [
    "final"
  ],
  "extends": [
    "zombie.core.textures.SmartTexture"
  ],
  "implements": [],
  "constructors": [
    {
      "scope": "package",
      "name": "CharacterSmartTexture",
      "describe": [],
      "args": []
    }
  ],
  "fields": [
    {
      "name": "BodyCategory",
      "scope": "public",
      "type": "int",
      "describe": [
        "static"
      ]
    },
    {
      "name": "ClothingBottomCategory",
      "scope": "public",
      "type": "int",
      "describe": [
        "static"
      ]
    },
    {
      "name": "ClothingTopCategory",
      "scope": "public",
      "type": "int",
      "describe": [
        "static"
      ]
    },
    {
      "name": "ClothingItemCategory",
      "scope": "public",
      "type": "int",
      "describe": [
        "static"
      ]
    },
    {
      "name": "DecalOverlayCategory",
      "scope": "public",
      "type": "int",
      "describe": [
        "static"
      ]
    },
    {
      "name": "DirtOverlayCategory",
      "scope": "public",
      "type": "int",
      "describe": [
        "static"
      ]
    },
    {
      "name": "java",
      "scope": "public",
      "type": "final",
      "describe": [
        "static"
      ]
    },
    {
      "name": "java",
      "scope": "public",
      "type": "final",
      "describe": [
        "static"
      ]
    },
    {
      "name": "java",
      "scope": "public",
      "type": "final",
      "describe": [
        "static"
      ]
    },
    {
      "name": "java",
      "scope": "public",
      "type": "final",
      "describe": [
        "static"
      ]
    }
  ],
  "methods": [
    {
      "scope": "public",
      "describe": [],
      "return": "void",
      "name": "setBlood",
      "args": [
        "zombie.characterTextures.BloodBodyPartType",
        "float"
      ]
    },
    {
      "scope": "public",
      "describe": [],
      "return": "void",
      "name": "setDirt",
      "args": [
        "zombie.characterTextures.BloodBodyPartType",
        "float"
      ]
    },
    {
      "scope": "public",
      "describe": [],
      "return": "void",
      "name": "removeBlood",
      "args": []
    },
    {
      "scope": "public",
      "describe": [],
      "return": "void",
      "name": "removeBlood",
      "args": [
        "zombie.characterTextures.BloodBodyPartType"
      ]
    },
    {
      "scope": "public",
      "describe": [],
      "return": "float",
      "name": "addBlood",
      "args": [
        "zombie.characterTextures.BloodBodyPartType",
        "float",
        "zombie.characters.IsoGameCharacter"
      ]
    },
    {
      "scope": "public",
      "describe": [],
      "return": "float",
      "name": "addDirt",
      "args": [
        "zombie.characterTextures.BloodBodyPartType",
        "float",
        "zombie.characters.IsoGameCharacter"
      ]
    },
    {
      "scope": "public",
      "describe": [],
      "return": "void",
      "name": "addShirtDecal",
      "args": [
        "java.lang.String"
      ]
    }
  ]
}