{
  "name": "GameKeyboard",
  "package": "zombie.input",
  "type": "class",
  "scope": "public",
  "describe": [
    "final"
  ],
  "extends": [],
  "implements": [],
  "constructors": [
    {
      "scope": "package",
      "name": "GameKeyboard",
      "describe": [],
      "args": []
    }
  ],
  "fields": [
    {
      "name": "bNoEventsWhileLoading",
      "scope": "public",
      "type": "boolean",
      "describe": [
        "static"
      ]
    },
    {
      "name": "doLuaKeyPressed",
      "scope": "public",
      "type": "boolean",
      "describe": [
        "static"
      ]
    }
  ],
  "methods": [
    {
      "scope": "public",
      "describe": [
        "static"
      ],
      "return": "void",
      "name": "update",
      "args": []
    },
    {
      "scope": "public",
      "describe": [
        "static"
      ],
      "return": "void",
      "name": "poll",
      "args": []
    },
    {
      "scope": "public",
      "describe": [
        "static"
      ],
      "return": "boolean",
      "name": "isKeyPressed",
      "args": [
        "int"
      ]
    },
    {
      "scope": "public",
      "describe": [
        "static"
      ],
      "return": "boolean",
      "name": "isKeyDown",
      "args": [
        "int"
      ]
    },
    {
      "scope": "public",
      "describe": [
        "static"
      ],
      "return": "boolean",
      "name": "wasKeyDown",
      "args": [
        "int"
      ]
    },
    {
      "scope": "public",
      "describe": [
        "static"
      ],
      "return": "void",
      "name": "eatKeyPress",
      "args": [
        "int"
      ]
    },
    {
      "scope": "public",
      "describe": [
        "static"
      ],
      "return": "void",
      "name": "setDoLuaKeyPressed",
      "args": [
        "boolean"
      ]
    },
    {
      "scope": "public",
      "describe": [
        "static"
      ],
      "return": "org.lwjglx.input.KeyEventQueue",
      "name": "getEventQueue",
      "args": []
    },
    {
      "scope": "public",
      "describe": [
        "static"
      ],
      "return": "org.lwjglx.input.KeyEventQueue",
      "name": "getEventQueuePolling",
      "args": []
    }
  ]
}